package wwe;

final class bKGb
{
    int pPxp;
    int Fuys;
    final String FXiO;
    int pPxp;
    int Fuys;
    final String FXiO;
    
    bKGb(final String fXiO) {
        this.FXiO = fXiO;
        super();
        this.pPxp = -1;
    }
    
    void pSOJ() {
        // 
        // This method could not be decompiled.
        // 
        // Original Bytecode:
        // 
        //     4: aload_0        
        //     5: aload_0        
        //     6: dup            
        //     7: getfield        wwe/bKGb.pPxp:I
        //    10: ldc             1
        //    12: iadd           
        //    13: dup_x1         
        //    14: putfield        wwe/bKGb.pPxp:I
        //    17: aload_0        
        //    18: getfield        wwe/bKGb.FXiO:Ljava/lang/String;
        //    21: invokevirtual   java/lang/String.length:()I
        //    24: if_icmpge       46
        //    27: aload_0        
        //    28: getfield        wwe/bKGb.FXiO:Ljava/lang/String;
        //    31: aload_0        
        //    32: getfield        wwe/bKGb.pPxp:I
        //    35: invokevirtual   java/lang/String.charAt:(I)C
        //    38: getstatic       wwe/bKGb.\u200b\u2003\u2009\u200f\u2002\u200a\u200f:Z
        //    41: ifeq            48
        //    44: aconst_null    
        //    45: athrow         
        //    46: ldc             -1
        //    48: putfield        wwe/bKGb.Fuys:I
        //    51: return         
        //    StackMapTable: 00 04 FC 00 03 01 00 69 07 00 02 FF 00 01 00 02 07 00 02 01 00 02 07 00 02 01
        // 
        throw new IllegalStateException("An error occurred while decompiling this method.");
    }
    
    boolean OWDW(final int p0) {
        // 
        // This method could not be decompiled.
        // 
        // Could not show original bytecode, likely due to the same error.
        // 
        throw new IllegalStateException("An error occurred while decompiling this method.");
    }
    
    bKGb(final String fXiO) {
        this.FXiO = fXiO;
        super();
        this.pPxp = -1;
    }
    
    void pSOJ() {
        // 
        // This method could not be decompiled.
        // 
        // Original Bytecode:
        // 
        //     4: aload_0        
        //     5: aload_0        
        //     6: dup            
        //     7: getfield        wwe/bKGb.pPxp:I
        //    10: ldc             1
        //    12: iadd           
        //    13: dup_x1         
        //    14: putfield        wwe/bKGb.pPxp:I
        //    17: aload_0        
        //    18: getfield        wwe/bKGb.FXiO:Ljava/lang/String;
        //    21: invokevirtual   java/lang/String.length:()I
        //    24: if_icmpge       46
        //    27: aload_0        
        //    28: getfield        wwe/bKGb.FXiO:Ljava/lang/String;
        //    31: aload_0        
        //    32: getfield        wwe/bKGb.pPxp:I
        //    35: invokevirtual   java/lang/String.charAt:(I)C
        //    38: getstatic       wwe/bKGb.\u200b\u2003\u2009\u200f\u2002\u200a\u200f:Z
        //    41: ifeq            48
        //    44: aconst_null    
        //    45: athrow         
        //    46: ldc             -1
        //    48: putfield        wwe/bKGb.Fuys:I
        //    51: return         
        // 
        throw new IllegalStateException("An error occurred while decompiling this method.");
    }
    
    boolean OWDW(final int n) {
        // 
        // This method could not be decompiled.
        // 
        // Original Bytecode:
        // 
        //     4: ireturn        
        //     5: aload_0        
        //     6: getfield        wwe/bKGb.Fuys:I
        //     9: ldc             32
        //    11: if_icmpne       30
        //    14: aload_0        
        //    15: invokevirtual   wwe/bKGb.pSOJ:()V
        //    18: getstatic       wwe/bKGb.\u200b\u2003\u2009\u200f\u2002\u200a\u200f:Z
        //    21: ifeq            5
        //    24: aconst_null    
        //    25: athrow         
        //    26: nop            
        //    27: nop            
        //    28: nop            
        //    29: athrow         
        //    30: aload_0        
        //    31: getfield        wwe/bKGb.Fuys:I
        //    34: iload_1        
        //    35: if_icmpne       49
        //    38: aload_0        
        //    39: invokevirtual   wwe/bKGb.pSOJ:()V
        //    42: ldc             1
        //    44: ireturn        
        //    45: nop            
        //    46: nop            
        //    47: nop            
        //    48: athrow         
        //    49: ldc             0
        //    51: ireturn        
        //    52: nop            
        //    53: nop            
        //    54: nop            
        //    55: athrow         
        // 
        throw new IllegalStateException("An error occurred while decompiling this method.");
    }
    
    double dKDh() {
        this.pSOJ();
        final double jhAq = this.jHAq();
        if (this.pPxp < this.FXiO.length()) {
            throw new RuntimeException("Unexpected: " + (char)this.Fuys);
        }
        return jhAq;
    }
    
    double jHAq() {
        // 
        // This method could not be decompiled.
        // 
        // Original Bytecode:
        // 
        //     4: dreturn        
        //     5: aload_0        
        //     6: invokevirtual   wwe/bKGb.qOlr:()D
        //     9: dstore_1       
        //    10: aload_0        
        //    11: ldc             43
        //    13: invokevirtual   wwe/bKGb.OWDW:(I)Z
        //    16: ifeq            38
        //    19: dload_1        
        //    20: aload_0        
        //    21: invokevirtual   wwe/bKGb.qOlr:()D
        //    24: dadd           
        //    25: dstore_1       
        //    26: getstatic       wwe/bKGb.\u200b\u2003\u2009\u200f\u2002\u200a\u200f:Z
        //    29: ifeq            10
        //    32: aconst_null    
        //    33: athrow         
        //    34: nop            
        //    35: nop            
        //    36: nop            
        //    37: athrow         
        //    38: aload_0        
        //    39: ldc             45
        //    41: invokevirtual   wwe/bKGb.OWDW:(I)Z
        //    44: ifeq            66
        //    47: dload_1        
        //    48: aload_0        
        //    49: invokevirtual   wwe/bKGb.qOlr:()D
        //    52: dsub           
        //    53: dstore_1       
        //    54: getstatic       wwe/bKGb.\u200b\u2003\u2009\u200f\u2002\u200a\u200f:Z
        //    57: ifeq            10
        //    60: aconst_null    
        //    61: athrow         
        //    62: nop            
        //    63: nop            
        //    64: nop            
        //    65: athrow         
        //    66: dload_1        
        //    67: dreturn        
        //    68: nop            
        //    69: nop            
        //    70: nop            
        //    71: athrow         
        // 
        throw new IllegalStateException("An error occurred while decompiling this method.");
    }
    
    double qOlr() {
        // 
        // This method could not be decompiled.
        // 
        // Original Bytecode:
        // 
        //     4: dreturn        
        //     5: aload_0        
        //     6: invokevirtual   wwe/bKGb.FgRQ:()D
        //     9: dstore_1       
        //    10: aload_0        
        //    11: ldc             42
        //    13: invokevirtual   wwe/bKGb.OWDW:(I)Z
        //    16: ifeq            38
        //    19: dload_1        
        //    20: aload_0        
        //    21: invokevirtual   wwe/bKGb.FgRQ:()D
        //    24: dmul           
        //    25: dstore_1       
        //    26: getstatic       wwe/bKGb.\u200b\u2003\u2009\u200f\u2002\u200a\u200f:Z
        //    29: ifeq            10
        //    32: aconst_null    
        //    33: athrow         
        //    34: nop            
        //    35: nop            
        //    36: nop            
        //    37: athrow         
        //    38: aload_0        
        //    39: ldc             47
        //    41: invokevirtual   wwe/bKGb.OWDW:(I)Z
        //    44: ifeq            66
        //    47: dload_1        
        //    48: aload_0        
        //    49: invokevirtual   wwe/bKGb.FgRQ:()D
        //    52: ddiv           
        //    53: dstore_1       
        //    54: getstatic       wwe/bKGb.\u200b\u2003\u2009\u200f\u2002\u200a\u200f:Z
        //    57: ifeq            10
        //    60: aconst_null    
        //    61: athrow         
        //    62: nop            
        //    63: nop            
        //    64: nop            
        //    65: athrow         
        //    66: dload_1        
        //    67: dreturn        
        //    68: nop            
        //    69: nop            
        //    70: nop            
        //    71: athrow         
        // 
        throw new IllegalStateException("An error occurred while decompiling this method.");
    }
    
    double FgRQ() {
        // 
        // This method could not be decompiled.
        // 
        // Original Bytecode:
        // 
        //     4: dreturn        
        //     5: aload_0        
        //     6: ldc             43
        //     8: invokevirtual   wwe/bKGb.OWDW:(I)Z
        //    11: ifeq            24
        //    14: aload_0        
        //    15: invokevirtual   wwe/bKGb.FgRQ:()D
        //    18: dreturn        
        //    19: nop            
        //    20: nop            
        //    21: nop            
        //    22: nop            
        //    23: athrow         
        //    24: aload_0        
        //    25: ldc             45
        //    27: invokevirtual   wwe/bKGb.OWDW:(I)Z
        //    30: ifeq            44
        //    33: aload_0        
        //    34: invokevirtual   wwe/bKGb.FgRQ:()D
        //    37: dneg           
        //    38: dreturn        
        //    39: nop            
        //    40: nop            
        //    41: nop            
        //    42: nop            
        //    43: athrow         
        //    44: aload_0        
        //    45: getfield        wwe/bKGb.pPxp:I
        //    48: istore_3       
        //    49: aload_0        
        //    50: ldc             40
        //    52: invokevirtual   wwe/bKGb.OWDW:(I)Z
        //    55: ifeq            83
        //    58: aload_0        
        //    59: invokevirtual   wwe/bKGb.jHAq:()D
        //    62: dstore_1       
        //    63: aload_0        
        //    64: ldc             41
        //    66: invokevirtual   wwe/bKGb.OWDW:(I)Z
        //    69: pop            
        //    70: getstatic       wwe/bKGb.\u200b\u2003\u2009\u200f\u2002\u200a\u200f:Z
        //    73: ifeq            458
        //    76: aconst_null    
        //    77: athrow         
        //    78: nop            
        //    79: nop            
        //    80: nop            
        //    81: nop            
        //    82: athrow         
        //    83: aload_0        
        //    84: getfield        wwe/bKGb.Fuys:I
        //    87: ldc             48
        //    89: if_icmplt       101
        //    92: aload_0        
        //    93: getfield        wwe/bKGb.Fuys:I
        //    96: ldc             57
        //    98: if_icmple       110
        //   101: aload_0        
        //   102: getfield        wwe/bKGb.Fuys:I
        //   105: ldc             46
        //   107: if_icmpne       183
        //   110: aload_0        
        //   111: getfield        wwe/bKGb.Fuys:I
        //   114: ldc             48
        //   116: if_icmplt       128
        //   119: aload_0        
        //   120: getfield        wwe/bKGb.Fuys:I
        //   123: ldc             57
        //   125: if_icmple       137
        //   128: aload_0        
        //   129: getfield        wwe/bKGb.Fuys:I
        //   132: ldc             46
        //   134: if_icmpne       154
        //   137: aload_0        
        //   138: invokevirtual   wwe/bKGb.pSOJ:()V
        //   141: getstatic       wwe/bKGb.\u200b\u2003\u2009\u200f\u2002\u200a\u200f:Z
        //   144: ifeq            110
        //   147: aconst_null    
        //   148: athrow         
        //   149: nop            
        //   150: nop            
        //   151: nop            
        //   152: nop            
        //   153: athrow         
        //   154: aload_0        
        //   155: getfield        wwe/bKGb.FXiO:Ljava/lang/String;
        //   158: iload_3        
        //   159: aload_0        
        //   160: getfield        wwe/bKGb.pPxp:I
        //   163: invokevirtual   java/lang/String.substring:(II)Ljava/lang/String;
        //   166: invokestatic    java/lang/Double.parseDouble:(Ljava/lang/String;)D
        //   169: dstore_1       
        //   170: getstatic       wwe/bKGb.\u200b\u2003\u2009\u200f\u2002\u200a\u200f:Z
        //   173: ifeq            458
        //   176: aconst_null    
        //   177: athrow         
        //   178: nop            
        //   179: nop            
        //   180: nop            
        //   181: nop            
        //   182: athrow         
        //   183: aload_0        
        //   184: getfield        wwe/bKGb.Fuys:I
        //   187: ldc             97
        //   189: if_icmplt       422
        //   192: aload_0        
        //   193: getfield        wwe/bKGb.Fuys:I
        //   196: ldc             122
        //   198: if_icmpgt       422
        //   201: aload_0        
        //   202: getfield        wwe/bKGb.Fuys:I
        //   205: ldc             97
        //   207: if_icmplt       236
        //   210: aload_0        
        //   211: getfield        wwe/bKGb.Fuys:I
        //   214: ldc             122
        //   216: if_icmpgt       236
        //   219: aload_0        
        //   220: invokevirtual   wwe/bKGb.pSOJ:()V
        //   223: getstatic       wwe/bKGb.\u200b\u2003\u2009\u200f\u2002\u200a\u200f:Z
        //   226: ifeq            201
        //   229: aconst_null    
        //   230: athrow         
        //   231: nop            
        //   232: nop            
        //   233: nop            
        //   234: nop            
        //   235: athrow         
        //   236: aload_0        
        //   237: getfield        wwe/bKGb.FXiO:Ljava/lang/String;
        //   240: iload_3        
        //   241: aload_0        
        //   242: getfield        wwe/bKGb.pPxp:I
        //   245: invokevirtual   java/lang/String.substring:(II)Ljava/lang/String;
        //   248: astore          4
        //   250: aload_0        
        //   251: invokevirtual   wwe/bKGb.FgRQ:()D
        //   254: dstore_1       
        //   255: aload           4
        //   257: ldc             "sqrt"
        //   259: invokevirtual   java/lang/String.equals:(Ljava/lang/Object;)Z
        //   262: ifeq            283
        //   265: dload_1        
        //   266: invokestatic    java/lang/Math.sqrt:(D)D
        //   269: dstore_1       
        //   270: getstatic       wwe/bKGb.\u200b\u2003\u2009\u200f\u2002\u200a\u200f:Z
        //   273: ifeq            409
        //   276: aconst_null    
        //   277: athrow         
        //   278: nop            
        //   279: nop            
        //   280: nop            
        //   281: nop            
        //   282: athrow         
        //   283: aload           4
        //   285: ldc             "sin"
        //   287: invokevirtual   java/lang/String.equals:(Ljava/lang/Object;)Z
        //   290: ifeq            314
        //   293: dload_1        
        //   294: invokestatic    java/lang/Math.toRadians:(D)D
        //   297: invokestatic    java/lang/Math.sin:(D)D
        //   300: dstore_1       
        //   301: getstatic       wwe/bKGb.\u200b\u2003\u2009\u200f\u2002\u200a\u200f:Z
        //   304: ifeq            409
        //   307: aconst_null    
        //   308: athrow         
        //   309: nop            
        //   310: nop            
        //   311: nop            
        //   312: nop            
        //   313: athrow         
        //   314: aload           4
        //   316: ldc             "cos"
        //   318: invokevirtual   java/lang/String.equals:(Ljava/lang/Object;)Z
        //   321: ifeq            345
        //   324: dload_1        
        //   325: invokestatic    java/lang/Math.toRadians:(D)D
        //   328: invokestatic    java/lang/Math.cos:(D)D
        //   331: dstore_1       
        //   332: getstatic       wwe/bKGb.\u200b\u2003\u2009\u200f\u2002\u200a\u200f:Z
        //   335: ifeq            409
        //   338: aconst_null    
        //   339: athrow         
        //   340: nop            
        //   341: nop            
        //   342: nop            
        //   343: nop            
        //   344: athrow         
        //   345: aload           4
        //   347: ldc             "tan"
        //   349: invokevirtual   java/lang/String.equals:(Ljava/lang/Object;)Z
        //   352: ifeq            376
        //   355: dload_1        
        //   356: invokestatic    java/lang/Math.toRadians:(D)D
        //   359: invokestatic    java/lang/Math.tan:(D)D
        //   362: dstore_1       
        //   363: getstatic       wwe/bKGb.\u200b\u2003\u2009\u200f\u2002\u200a\u200f:Z
        //   366: ifeq            409
        //   369: aconst_null    
        //   370: athrow         
        //   371: nop            
        //   372: nop            
        //   373: nop            
        //   374: nop            
        //   375: athrow         
        //   376: new             Ljava/lang/RuntimeException;
        //   379: dup            
        //   380: new             Ljava/lang/StringBuilder;
        //   383: dup            
        //   384: invokespecial   java/lang/StringBuilder.<init>:()V
        //   387: ldc             "Unknown function: "
        //   389: invokevirtual   java/lang/StringBuilder.append:(Ljava/lang/String;)Ljava/lang/StringBuilder;
        //   392: aload           4
        //   394: invokevirtual   java/lang/StringBuilder.append:(Ljava/lang/String;)Ljava/lang/StringBuilder;
        //   397: invokevirtual   java/lang/StringBuilder.toString:()Ljava/lang/String;
        //   400: invokespecial   java/lang/RuntimeException.<init>:(Ljava/lang/String;)V
        //   403: athrow         
        //   404: nop            
        //   405: nop            
        //   406: nop            
        //   407: nop            
        //   408: athrow         
        //   409: getstatic       wwe/bKGb.\u200b\u2003\u2009\u200f\u2002\u200a\u200f:Z
        //   412: ifeq            458
        //   415: aconst_null    
        //   416: athrow         
        //   417: nop            
        //   418: nop            
        //   419: nop            
        //   420: nop            
        //   421: athrow         
        //   422: new             Ljava/lang/RuntimeException;
        //   425: dup            
        //   426: new             Ljava/lang/StringBuilder;
        //   429: dup            
        //   430: invokespecial   java/lang/StringBuilder.<init>:()V
        //   433: ldc             "Unexpected: "
        //   435: invokevirtual   java/lang/StringBuilder.append:(Ljava/lang/String;)Ljava/lang/StringBuilder;
        //   438: aload_0        
        //   439: getfield        wwe/bKGb.Fuys:I
        //   442: i2c            
        //   443: invokevirtual   java/lang/StringBuilder.append:(C)Ljava/lang/StringBuilder;
        //   446: invokevirtual   java/lang/StringBuilder.toString:()Ljava/lang/String;
        //   449: invokespecial   java/lang/RuntimeException.<init>:(Ljava/lang/String;)V
        //   452: athrow         
        //   453: nop            
        //   454: nop            
        //   455: nop            
        //   456: nop            
        //   457: athrow         
        //   458: aload_0        
        //   459: ldc             94
        //   461: invokevirtual   wwe/bKGb.OWDW:(I)Z
        //   464: ifeq            476
        //   467: dload_1        
        //   468: aload_0        
        //   469: invokevirtual   wwe/bKGb.FgRQ:()D
        //   472: invokestatic    java/lang/Math.pow:(DD)D
        //   475: dstore_1       
        //   476: dload_1        
        //   477: dreturn        
        //   478: nop            
        //   479: nop            
        //   480: nop            
        //   481: nop            
        //   482: athrow         
        // 
        throw new IllegalStateException("An error occurred while decompiling this method.");
    }
}
