package wwe;

class dorv extends Thread
{
    final KULU oMGm;
    
    dorv(final KULU omGm) {
        this.oMGm = omGm;
        super();
    }
    
    @Override
    public void run() {
        // 
        // This method could not be decompiled.
        // 
        // Original Bytecode:
        // 
        //     3: return         
        //     4: invokestatic    wwe/vlwv.wNWV:()V
        //     7: getstatic       wwe/vlwv.wMQO:Lwwe/sbfc;
        //    10: invokevirtual   wwe/sbfc.BBwj:()V
        //    13: getstatic       wwe/dorv.\u2007\u2005\u2008\u2000\u200c\u2009:Z
        //    16: ifeq            26
        //    19: aconst_null    
        //    20: athrow         
        //    21: astore_1       
        //    22: aload_1        
        //    23: invokevirtual   java/lang/Exception.printStackTrace:()V
        //    26: return         
        //    27: nop            
        //    28: nop            
        //    29: nop            
        //    30: athrow         
        //    StackMapTable: 00 05 FD 00 03 00 01 00 50 07 00 17 04 FF 00 00 00 00 00 01 07 00 0F
        //    Exceptions:
        //  Try           Handler
        //  Start  End    Start  End    Type                 
        //  -----  -----  -----  -----  ---------------------
        //  4      13     21     26     Ljava/lang/Exception;
        // 
        throw new IllegalStateException("An error occurred while decompiling this method.");
    }
}
