package wwe;

import java.net.*;
import java.io.*;

class YlQN extends Thread
{
    final File IMXx;
    final boolean EaJp;
    final PzCC JRJc;
    
    YlQN(final PzCC jrJc, final File imXx, final boolean eaJp) {
        this.JRJc = jrJc;
        this.IMXx = imXx;
        this.EaJp = eaJp;
        super();
    }
    
    @Override
    public void run() {
        // 
        // This method could not be decompiled.
        // 
        // Original Bytecode:
        // 
        //     3: return         
        //     4: aconst_null    
        //     5: astore_1       
        //     6: aconst_null    
        //     7: astore_2       
        //     8: aload_0        
        //     9: getfield        wwe/YlQN.JRJc:Lwwe/PzCC;
        //    12: invokestatic    wwe/PzCC.XXkX:(Lwwe/PzCC;)Lwwe/rfyb;
        //    15: aload_0        
        //    16: getfield        wwe/YlQN.JRJc:Lwwe/PzCC;
        //    19: invokestatic    wwe/PzCC.rDJM:(Lwwe/PzCC;)J
        //    22: invokevirtual   wwe/rfyb.Lodk:(J)[I
        //    25: checkcast       [I
        //    28: astore_3       
        //    29: new             Ljava/lang/StringBuilder;
        //    32: dup            
        //    33: invokespecial   java/lang/StringBuilder.<init>:()V
        //    36: aload_3        
        //    37: ldc             0
        //    39: iaload         
        //    40: invokevirtual   java/lang/StringBuilder.append:(I)Ljava/lang/StringBuilder;
        //    43: ldc             "."
        //    45: invokevirtual   java/lang/StringBuilder.append:(Ljava/lang/String;)Ljava/lang/StringBuilder;
        //    48: aload_3        
        //    49: ldc             1
        //    51: iaload         
        //    52: invokevirtual   java/lang/StringBuilder.append:(I)Ljava/lang/StringBuilder;
        //    55: ldc             "."
        //    57: invokevirtual   java/lang/StringBuilder.append:(Ljava/lang/String;)Ljava/lang/StringBuilder;
        //    60: aload_3        
        //    61: ldc             2
        //    63: iaload         
        //    64: invokevirtual   java/lang/StringBuilder.append:(I)Ljava/lang/StringBuilder;
        //    67: ldc             "."
        //    69: invokevirtual   java/lang/StringBuilder.append:(Ljava/lang/String;)Ljava/lang/StringBuilder;
        //    72: aload_3        
        //    73: ldc             3
        //    75: iaload         
        //    76: invokevirtual   java/lang/StringBuilder.append:(I)Ljava/lang/StringBuilder;
        //    79: invokevirtual   java/lang/StringBuilder.toString:()Ljava/lang/String;
        //    82: astore          4
        //    84: aload_0        
        //    85: getfield        wwe/YlQN.JRJc:Lwwe/PzCC;
        //    88: new             Ljava/net/Socket;
        //    91: dup            
        //    92: aload           4
        //    94: aload_0        
        //    95: getfield        wwe/YlQN.JRJc:Lwwe/PzCC;
        //    98: invokestatic    wwe/PzCC.qwqA:(Lwwe/PzCC;)I
        //   101: invokespecial   java/net/Socket.<init>:(Ljava/lang/String;I)V
        //   104: invokestatic    wwe/PzCC.YrOU:(Lwwe/PzCC;Ljava/net/Socket;)Ljava/net/Socket;
        //   107: pop            
        //   108: aload_0        
        //   109: getfield        wwe/YlQN.JRJc:Lwwe/PzCC;
        //   112: invokestatic    wwe/PzCC.oDup:(Lwwe/PzCC;)Ljava/net/Socket;
        //   115: ldc             30000
        //   117: invokevirtual   java/net/Socket.setSoTimeout:(I)V
        //   120: aload_0        
        //   121: getfield        wwe/YlQN.JRJc:Lwwe/PzCC;
        //   124: invokestatic    java/lang/System.currentTimeMillis:()J
        //   127: invokestatic    wwe/PzCC.MyqF:(Lwwe/PzCC;J)J
        //   130: pop2           
        //   131: aload_0        
        //   132: getfield        wwe/YlQN.JRJc:Lwwe/PzCC;
        //   135: invokestatic    wwe/PzCC.cRIJ:(Lwwe/PzCC;)Lwwe/iroq;
        //   138: aload_0        
        //   139: getfield        wwe/YlQN.JRJc:Lwwe/PzCC;
        //   142: invokevirtual   wwe/iroq.JJDC:(Lwwe/PzCC;)V
        //   145: new             Ljava/io/BufferedInputStream;
        //   148: dup            
        //   149: aload_0        
        //   150: getfield        wwe/YlQN.JRJc:Lwwe/PzCC;
        //   153: invokestatic    wwe/PzCC.oDup:(Lwwe/PzCC;)Ljava/net/Socket;
        //   156: invokevirtual   java/net/Socket.getInputStream:()Ljava/io/InputStream;
        //   159: invokespecial   java/io/BufferedInputStream.<init>:(Ljava/io/InputStream;)V
        //   162: astore          5
        //   164: new             Ljava/io/BufferedOutputStream;
        //   167: dup            
        //   168: aload_0        
        //   169: getfield        wwe/YlQN.JRJc:Lwwe/PzCC;
        //   172: invokestatic    wwe/PzCC.oDup:(Lwwe/PzCC;)Ljava/net/Socket;
        //   175: invokevirtual   java/net/Socket.getOutputStream:()Ljava/io/OutputStream;
        //   178: invokespecial   java/io/BufferedOutputStream.<init>:(Ljava/io/OutputStream;)V
        //   181: astore          6
        //   183: new             Ljava/io/BufferedOutputStream;
        //   186: dup            
        //   187: new             Ljava/io/FileOutputStream;
        //   190: dup            
        //   191: aload_0        
        //   192: getfield        wwe/YlQN.IMXx:Ljava/io/File;
        //   195: invokevirtual   java/io/File.getCanonicalPath:()Ljava/lang/String;
        //   198: aload_0        
        //   199: getfield        wwe/YlQN.EaJp:Z
        //   202: invokespecial   java/io/FileOutputStream.<init>:(Ljava/lang/String;Z)V
        //   205: invokespecial   java/io/BufferedOutputStream.<init>:(Ljava/io/OutputStream;)V
        //   208: astore_1       
        //   209: ldc             1024
        //   211: newarray        B
        //   213: astore          7
        //   215: ldc             4
        //   217: newarray        B
        //   219: astore          8
        //   221: ldc             0
        //   223: istore          9
        //   225: aload           5
        //   227: aload           7
        //   229: ldc             0
        //   231: aload           7
        //   233: arraylength    
        //   234: invokevirtual   java/io/BufferedInputStream.read:([BII)I
        //   237: dup            
        //   238: istore          9
        //   240: ldc             -1
        //   242: if_icmpeq       430
        //   245: aload_1        
        //   246: aload           7
        //   248: ldc             0
        //   250: iload           9
        //   252: invokevirtual   java/io/BufferedOutputStream.write:([BII)V
        //   255: aload_0        
        //   256: getfield        wwe/YlQN.JRJc:Lwwe/PzCC;
        //   259: aload_0        
        //   260: getfield        wwe/YlQN.JRJc:Lwwe/PzCC;
        //   263: invokestatic    wwe/PzCC.Usxc:(Lwwe/PzCC;)J
        //   266: iload           9
        //   268: i2l            
        //   269: ladd           
        //   270: invokestatic    wwe/PzCC.ioUv:(Lwwe/PzCC;J)J
        //   273: pop2           
        //   274: aload           8
        //   276: ldc             0
        //   278: aload_0        
        //   279: getfield        wwe/YlQN.JRJc:Lwwe/PzCC;
        //   282: invokestatic    wwe/PzCC.Usxc:(Lwwe/PzCC;)J
        //   285: ldc             24
        //   287: lshr           
        //   288: ldc2_w          -1218177997522080238
        //   291: ldc2_w          -2665073605485002411
        //   294: dup2_x2        
        //   295: pop2           
        //   296: pop2           
        //   297: ldc2_w          -2665073605485002326
        //   300: lxor           
        //   301: land           
        //   302: l2i            
        //   303: i2b            
        //   304: bastore        
        //   305: aload           8
        //   307: ldc             1
        //   309: aload_0        
        //   310: getfield        wwe/YlQN.JRJc:Lwwe/PzCC;
        //   313: invokestatic    wwe/PzCC.Usxc:(Lwwe/PzCC;)J
        //   316: ldc             16
        //   318: lshr           
        //   319: ldc2_w          3764980722838864478
        //   322: ldc2_w          4540499820776736764
        //   325: dup2_x2        
        //   326: pop2           
        //   327: pop2           
        //   328: ldc2_w          4540499820776736515
        //   331: lxor           
        //   332: land           
        //   333: l2i            
        //   334: i2b            
        //   335: bastore        
        //   336: aload           8
        //   338: ldc             2
        //   340: aload_0        
        //   341: getfield        wwe/YlQN.JRJc:Lwwe/PzCC;
        //   344: invokestatic    wwe/PzCC.Usxc:(Lwwe/PzCC;)J
        //   347: ldc             8
        //   349: lshr           
        //   350: ldc2_w          -911533620020289414
        //   353: ldc2_w          -5603788404611082111
        //   356: dup2_x2        
        //   357: pop2           
        //   358: pop2           
        //   359: ldc2_w          -5603788404611082114
        //   362: lxor           
        //   363: land           
        //   364: l2i            
        //   365: i2b            
        //   366: bastore        
        //   367: aload           8
        //   369: ldc             3
        //   371: aload_0        
        //   372: getfield        wwe/YlQN.JRJc:Lwwe/PzCC;
        //   375: invokestatic    wwe/PzCC.Usxc:(Lwwe/PzCC;)J
        //   378: ldc             0
        //   380: lshr           
        //   381: ldc2_w          8677053018295738047
        //   384: ldc2_w          3625348693931215519
        //   387: dup2_x2        
        //   388: pop2           
        //   389: pop2           
        //   390: ldc2_w          3625348693931215456
        //   393: lxor           
        //   394: land           
        //   395: l2i            
        //   396: i2b            
        //   397: bastore        
        //   398: aload           6
        //   400: aload           8
        //   402: invokevirtual   java/io/BufferedOutputStream.write:([B)V
        //   405: aload           6
        //   407: invokevirtual   java/io/BufferedOutputStream.flush:()V
        //   410: aload_0        
        //   411: getfield        wwe/YlQN.JRJc:Lwwe/PzCC;
        //   414: invokestatic    wwe/PzCC.kZLg:(Lwwe/PzCC;)V
        //   417: getstatic       wwe/YlQN.\u200b\u2005\u2003\u200e\u2005:Z
        //   420: ifeq            225
        //   423: aconst_null    
        //   424: athrow         
        //   425: nop            
        //   426: nop            
        //   427: nop            
        //   428: nop            
        //   429: athrow         
        //   430: aload_1        
        //   431: invokevirtual   java/io/BufferedOutputStream.flush:()V
        //   434: aload_1        
        //   435: invokevirtual   java/io/BufferedOutputStream.close:()V
        //   438: aload_0        
        //   439: getfield        wwe/YlQN.JRJc:Lwwe/PzCC;
        //   442: invokestatic    wwe/PzCC.oDup:(Lwwe/PzCC;)Ljava/net/Socket;
        //   445: invokevirtual   java/net/Socket.close:()V
        //   448: getstatic       wwe/YlQN.\u200b\u2005\u2003\u200e\u2005:Z
        //   451: ifeq            533
        //   454: aconst_null    
        //   455: athrow         
        //   456: astore_3       
        //   457: getstatic       wwe/YlQN.\u200b\u2005\u2003\u200e\u2005:Z
        //   460: ifeq            533
        //   463: aconst_null    
        //   464: athrow         
        //   465: astore_3       
        //   466: aload_3        
        //   467: astore_2       
        //   468: aload_1        
        //   469: invokevirtual   java/io/BufferedOutputStream.close:()V
        //   472: aload_0        
        //   473: getfield        wwe/YlQN.JRJc:Lwwe/PzCC;
        //   476: invokestatic    wwe/PzCC.oDup:(Lwwe/PzCC;)Ljava/net/Socket;
        //   479: invokevirtual   java/net/Socket.close:()V
        //   482: getstatic       wwe/YlQN.\u200b\u2005\u2003\u200e\u2005:Z
        //   485: ifeq            533
        //   488: aconst_null    
        //   489: athrow         
        //   490: astore_3       
        //   491: getstatic       wwe/YlQN.\u200b\u2005\u2003\u200e\u2005:Z
        //   494: ifeq            533
        //   497: aconst_null    
        //   498: athrow         
        //   499: astore          10
        //   501: aload_1        
        //   502: invokevirtual   java/io/BufferedOutputStream.close:()V
        //   505: aload_0        
        //   506: getfield        wwe/YlQN.JRJc:Lwwe/PzCC;
        //   509: invokestatic    wwe/PzCC.oDup:(Lwwe/PzCC;)Ljava/net/Socket;
        //   512: invokevirtual   java/net/Socket.close:()V
        //   515: getstatic       wwe/YlQN.\u200b\u2005\u2003\u200e\u2005:Z
        //   518: ifeq            525
        //   521: aconst_null    
        //   522: athrow         
        //   523: astore          11
        //   525: aload           10
        //   527: athrow         
        //   528: nop            
        //   529: nop            
        //   530: nop            
        //   531: nop            
        //   532: athrow         
        //   533: aload_0        
        //   534: getfield        wwe/YlQN.JRJc:Lwwe/PzCC;
        //   537: invokestatic    wwe/PzCC.XXkX:(Lwwe/PzCC;)Lwwe/rfyb;
        //   540: aload_0        
        //   541: getfield        wwe/YlQN.JRJc:Lwwe/PzCC;
        //   544: aload_2        
        //   545: invokevirtual   wwe/rfyb.PmDi:(Lwwe/PzCC;Ljava/lang/Exception;)V
        //   548: return         
        //   549: nop            
        //   550: nop            
        //   551: nop            
        //   552: nop            
        //   553: athrow         
        //    StackMapTable: 00 0E FF 00 03 00 0D 07 00 02 00 00 00 00 00 00 00 00 00 00 00 01 00 00 00 FF 00 DC 00 0D 07 00 02 07 00 7A 05 07 00 31 07 00 8D 07 00 71 07 00 7A 07 00 8F 07 00 8F 01 00 00 01 00 00 FF 00 C7 00 00 00 01 07 00 13 FF 00 04 00 0D 07 00 02 07 00 7A 05 07 00 31 07 00 8D 07 00 71 07 00 7A 07 00 8F 07 00 8F 01 00 00 01 00 00 59 07 00 21 FF 00 08 00 0D 07 00 02 07 00 7A 05 00 00 00 00 00 00 00 00 00 01 00 01 07 00 21 FF 00 18 00 0D 07 00 02 07 00 7A 07 00 21 07 00 21 00 00 00 00 00 00 00 00 01 00 01 07 00 21 FF 00 08 00 0D 07 00 02 07 00 7A 07 00 21 00 00 00 00 00 00 00 00 00 01 00 01 07 00 13 FF 00 17 00 0D 07 00 02 07 00 7A 07 00 21 00 00 00 00 00 00 00 07 00 13 00 01 00 01 07 00 21 01 FF 00 02 00 00 00 01 07 00 13 FF 00 04 00 0D 07 00 02 07 00 7A 07 00 21 07 00 CB 00 00 00 00 00 00 00 00 01 00 00 FF 00 0F 00 00 00 01 07 00 13
        //    Exceptions:
        //  Try           Handler
        //  Start  End    Start  End    Type                 
        //  -----  -----  -----  -----  ---------------------
        //  434    448    456    465    Ljava/lang/Exception;
        //  8      425    465    499    Ljava/lang/Exception;
        //  430    434    465    499    Ljava/lang/Exception;
        //  468    482    490    499    Ljava/lang/Exception;
        //  8      425    499    528    Any
        //  430    434    499    528    Any
        //  465    468    499    528    Any
        //  501    515    523    525    Ljava/lang/Exception;
        //  499    501    499    528    Any
        // 
        throw new IllegalStateException("An error occurred while decompiling this method.");
    }
}
